pysecxbrl/XMLExtract.py
pysecxbrl/__init__.py
pysecxbrl/extract.py
pysecxbrl/parsing.py
py_sec_xbrl-0.2.dist-info/LICENSE
py_sec_xbrl-0.2.dist-info/METADATA
py_sec_xbrl-0.2.dist-info/WHEEL
py_sec_xbrl-0.2.dist-info/top_level.txt
py_sec_xbrl-0.2.dist-info/RECORD
