Metadata-Version: 2.1
Name: py-sec-xbrl
Version: 0.2
Summary: SEC EDGAR Parser based on Python 3
Home-page: https://github.com/zhaolewen/py-sec-xbrl
Author: Lewen Zhao
Author-email: zhaolewen@gmail.com
License: UNKNOWN
Platform: UNKNOWN
Classifier: Programming Language :: Python :: 3
Classifier: License :: OSI Approved :: MIT License
Classifier: Operating System :: OS Independent
